rinoh_mscorefontinstaller.py
rinoh_mscorefontinstaller-0.1.0.dist-info/LICENSE
rinoh_mscorefontinstaller-0.1.0.dist-info/WHEEL
rinoh_mscorefontinstaller-0.1.0.dist-info/METADATA
rinoh_mscorefontinstaller-0.1.0.dist-info/RECORD
