Metadata-Version: 2.1
Name: rinoh-mscorefontinstaller
Version: 0.1.0
Summary: Helper package to install Microsoft's Core fonts for the Web
Home-page: https://github.com/brechtm/rinoh-mscorefonts
License: BSD-3-Clause
Keywords: fonts,truetype
Author: Brecht Machiels
Author-email: brecht@mos6581.org
Requires-Python: >=3.7.0,<4.0.0
Classifier: Intended Audience :: Developers
Classifier: Intended Audience :: End Users/Desktop
Classifier: License :: OSI Approved :: BSD License
Classifier: Operating System :: OS Independent
Classifier: Programming Language :: Python :: 3
Classifier: Programming Language :: Python :: 3.10
Classifier: Programming Language :: Python :: 3.7
Classifier: Programming Language :: Python :: 3.8
Classifier: Programming Language :: Python :: 3.9
Classifier: Topic :: Printing
Classifier: Topic :: Software Development :: Libraries :: Python Modules
Classifier: Topic :: Text Processing :: Fonts
Requires-Dist: hachoir (==3.1.3)
Project-URL: Repository, https://github.com/brechtm/rinoh-mscorefonts
